{
  "$schema": "https://raw.githubusercontent.com/spdx/spdx-spec/v2.2.1/schemas/spdx-schema.json",
  "spdxVersion": "SPDX-2.2",
  "dataLicense": "CC0-1.0",
  "SPDXID": "SPDXRef-DOCUMENT",
  "documentNamespace": "https://spdx.org/spdxdocs/boost-winapi-x64-windows-1.84.0-0d901814-d75c-4e65-9320-5415892add89",
  "name": "boost-winapi:x64-windows@1.84.0 5be26b224fe7aaa7f55997df906d82e72214c38f636721a10de85e028a42b9f6",
  "creationInfo": {
    "creators": [
      "Tool: vcpkg-8a83681f921b10d86ae626fd833c253f4f8c355b"
    ],
    "created": "2024-02-11T21:37:27Z"
  },
  "relationships": [
    {
      "spdxElementId": "SPDXRef-port",
      "relationshipType": "GENERATES",
      "relatedSpdxElement": "SPDXRef-binary"
    },
    {
      "spdxElementId": "SPDXRef-port",
      "relationshipType": "CONTAINS",
      "relatedSpdxElement": "SPDXRef-file-0"
    },
    {
      "spdxElementId": "SPDXRef-port",
      "relationshipType": "CONTAINS",
      "relatedSpdxElement": "SPDXRef-file-1"
    },
    {
      "spdxElementId": "SPDXRef-binary",
      "relationshipType": "GENERATED_FROM",
      "relatedSpdxElement": "SPDXRef-port"
    },
    {
      "spdxElementId": "SPDXRef-file-0",
      "relationshipType": "CONTAINED_BY",
      "relatedSpdxElement": "SPDXRef-port"
    },
    {
      "spdxElementId": "SPDXRef-file-1",
      "relationshipType": "CONTAINED_BY",
      "relatedSpdxElement": "SPDXRef-port"
    }
  ],
  "packages": [
    {
      "name": "boost-winapi",
      "SPDXID": "SPDXRef-port",
      "versionInfo": "1.84.0",
      "downloadLocation": "git+https://github.com/Microsoft/vcpkg#ports/boost-winapi",
      "homepage": "https://github.com/boostorg/winapi",
      "licenseConcluded": "BSL-1.0",
      "licenseDeclared": "NOASSERTION",
      "copyrightText": "NOASSERTION",
      "description": "Boost winapi module",
      "comment": "This is the port (recipe) consumed by vcpkg."
    },
    {
      "name": "boost-winapi:x64-windows",
      "SPDXID": "SPDXRef-binary",
      "versionInfo": "5be26b224fe7aaa7f55997df906d82e72214c38f636721a10de85e028a42b9f6",
      "downloadLocation": "NONE",
      "licenseConcluded": "BSL-1.0",
      "licenseDeclared": "NOASSERTION",
      "copyrightText": "NOASSERTION",
      "comment": "This is a binary package built by vcpkg."
    },
    {
      "SPDXID": "SPDXRef-resource-1",
      "name": "boostorg/winapi",
      "downloadLocation": "git+https://github.com/boostorg/winapi@boost-1.84.0",
      "licenseConcluded": "NOASSERTION",
      "licenseDeclared": "NOASSERTION",
      "copyrightText": "NOASSERTION",
      "checksums": [
        {
          "algorithm": "SHA512",
          "checksumValue": "f0d04dcdcb930f88ec47f6580bce94258bac492e885422eb67ed2d9980d066cc46f969bd6aac29687fcc3f98a252b872df5dadfb1db19fe61cb1ddbacb70f925"
        }
      ]
    }
  ],
  "files": [
    {
      "fileName": "./C:/Users/franc/OneDrive/Documents/vcpkg/ports/boost-winapi/portfile.cmake",
      "SPDXID": "SPDXRef-file-0",
      "checksums": [
        {
          "algorithm": "SHA256",
          "checksumValue": "e0d5142f9bd35bb0356a1b16a8e29f76de73bed63af66c7a88e0222bae287cbd"
        }
      ],
      "licenseConcluded": "NOASSERTION",
      "copyrightText": "NOASSERTION"
    },
    {
      "fileName": "./C:/Users/franc/OneDrive/Documents/vcpkg/ports/boost-winapi/vcpkg.json",
      "SPDXID": "SPDXRef-file-1",
      "checksums": [
        {
          "algorithm": "SHA256",
          "checksumValue": "7bcb8c7831baafa4ccc9078c2af03dad2b367501cad79ca99031b680e6afebeb"
        }
      ],
      "licenseConcluded": "NOASSERTION",
      "copyrightText": "NOASSERTION"
    }
  ]
}
